arxivbox/__init__.py
arxivbox/__main__.py
arxivbox/arxivbox.py
arxivbox-1.0.6.dist-info/METADATA
arxivbox-1.0.6.dist-info/WHEEL
arxivbox-1.0.6.dist-info/top_level.txt
arxivbox-1.0.6.dist-info/RECORD
